build/lib/build/lib/rpyt/__init__.py
build/lib/build/lib/rpyt/__main__.py
build/lib/build/lib/rpyt/common.py
build/lib/build/lib/rpyt/l10n/__init__.py
build/lib/build/lib/rpyt/l10n/common.py
build/lib/build/lib/rpyt/l10n/processors/__init__.py
build/lib/build/lib/rpyt/l10n/processors/crowdin_json_with_context_processor.py
build/lib/build/lib/rpyt/l10n/processors/dynamic_json_processor.py
build/lib/build/lib/rpyt/l10n/processors/json_processor.py
build/lib/build/lib/rpyt/l10n/processors/processor.py
build/lib/rpyt/__init__.py
build/lib/rpyt/__main__.py
build/lib/rpyt/common.py
build/lib/rpyt/l10n/__init__.py
build/lib/rpyt/l10n/common.py
build/lib/rpyt/l10n/processors/__init__.py
build/lib/rpyt/l10n/processors/crowdin_json_with_context_processor.py
build/lib/rpyt/l10n/processors/dynamic_json_processor.py
build/lib/rpyt/l10n/processors/json_processor.py
build/lib/rpyt/l10n/processors/processor.py
rpyt/__init__.py
rpyt/__main__.py
rpyt/common.py
rpyt/l10n/__init__.py
rpyt/l10n/common.py
rpyt/l10n/processors/__init__.py
rpyt/l10n/processors/crowdin_json_with_context_processor.py
rpyt/l10n/processors/dynamic_json_processor.py
rpyt/l10n/processors/json_processor.py
rpyt/l10n/processors/processor.py
rpyt/resources/common.rpym.txt
rpyt-0.17.dist-info/METADATA
rpyt-0.17.dist-info/WHEEL
rpyt-0.17.dist-info/entry_points.txt
rpyt-0.17.dist-info/top_level.txt
rpyt-0.17.dist-info/RECORD
