Metadata-Version: 2.1
Name: rpyt
Version: 0.17
Requires-Dist: fire
